sas/__init__.py
sas/downloader.py
sasdescargezero-0.1.2.dist-info/licenses/LICENSE
sasdescargezero-0.1.2.dist-info/METADATA
sasdescargezero-0.1.2.dist-info/WHEEL
sasdescargezero-0.1.2.dist-info/top_level.txt
sasdescargezero-0.1.2.dist-info/RECORD
