Metadata-Version: 2.4
Name: sasdescargezero
Version: 0.1.2
Summary: Una librería Python para descargar archivos desde un host específico
Home-page: https://github.com/tuusuario/sas
Author: Sas
Author-email: ri6k751ni@nine.testrun.org
Classifier: Programming Language :: Python :: 3
Classifier: License :: OSI Approved :: MIT License
Classifier: Operating System :: OS Independent
Requires-Python: >=3.6
License-File: LICENSE
Requires-Dist: requests>=2.28.0
Requires-Dist: beautifulsoup4>=4.11.0
Requires-Dist: urllib3>=1.26.0
Dynamic: author
Dynamic: author-email
Dynamic: classifier
Dynamic: description
Dynamic: description-content-type
Dynamic: home-page
Dynamic: license-file
Dynamic: requires-dist
Dynamic: requires-python
Dynamic: summary
